{
  "meta": {
    "source": "国家医疗保障局·两库规则库框架体系（1.0版）",
    "ref_id": "KB1-两库框架-医疗保障基金智能审核和监控规则库框架体系-1-0",
    "extracted_at": "2026-07-03",
    "total": 79,
    "code_prefixes": {
      "GZ": 71,
      "ZB": 8
    }
  },
  "rules_flat": [
    {
      "official_code": "GZ10000101001000",
      "tier1": "政策类",
      "tier2": "药品政策限定类",
      "tier1_id": "policy",
      "tier2_id": "drug_policy",
      "name": "药品限工伤保险",
      "definition": "对《国家基本医疗保险、工伤保险和生育保 险药品目录》及《医保药品分类与代码数据 库》对限工伤保险的药品进行监管。"
    },
    {
      "official_code": "GZ10000101002000",
      "tier1": "政策类",
      "tier2": "药品政策限定类",
      "tier1_id": "policy",
      "tier2_id": "drug_policy",
      "name": "药品限生育保险",
      "definition": "对《国家基本医疗保险、工伤保险和生育保 险药品目录》及《医保药品分类与代码数据 库》对限生育保险的药品进行监管。"
    },
    {
      "official_code": "GZ10000101003000",
      "tier1": "政策类",
      "tier2": "药品政策限定类",
      "tier1_id": "policy",
      "tier2_id": "drug_policy",
      "name": "中药饮片单复方均不予支付",
      "definition": "对《国家基本医疗保险、工伤保险和生育保 险药品目录》及《医保药品分类与代码数据 库》对不得纳入基金支付范围的中药饮片进 行监管。"
    },
    {
      "official_code": "GZ10000101004000",
      "tier1": "政策类",
      "tier2": "药品政策限定类",
      "tier1_id": "policy",
      "tier2_id": "drug_policy",
      "name": "中药饮片单方使用不予支付",
      "definition": "对《国家基本医疗保险、工伤保险和生育保 险药品目录》及《医保药品分类与代码数据 库》对单独使用且全部由这些饮片组成的处 方也不予支付的中药饮片进行监管。"
    },
    {
      "official_code": "GZ10000101005000",
      "tier1": "政策类",
      "tier2": "药品政策限定类",
      "tier1_id": "policy",
      "tier2_id": "drug_policy",
      "name": "药品限二线使用",
      "definition": "对《国家基本医疗保险、工伤保险和生育保 险药品目录》及《医保药品分类与代码数据 库》中限二线使用的药品进行监管。"
    },
    {
      "official_code": "GZ10000101006000",
      "tier1": "政策类",
      "tier2": "药品政策限定类",
      "tier1_id": "policy",
      "tier2_id": "drug_policy",
      "name": "药品限新生儿使用",
      "definition": "对《国家基本医疗保险、工伤保险和生育保 险药品目录》及《医保药品分类与代码数据 库》中限新生儿使用的药品进行监管。"
    },
    {
      "official_code": "GZ10000101007000",
      "tier1": "政策类",
      "tier2": "药品政策限定类",
      "tier1_id": "policy",
      "tier2_id": "drug_policy",
      "name": "药品限儿童使用",
      "definition": "对《国家基本医疗保险、工伤保险和生育保 险药品目录》及《医保药品分类与代码数据 库》中限儿童使用的药品进行监管。"
    },
    {
      "official_code": "GZ10000101008000",
      "tier1": "政策类",
      "tier2": "药品政策限定类",
      "tier1_id": "policy",
      "tier2_id": "drug_policy",
      "name": "药品限适应症",
      "definition": "对《国家基本医疗保险、工伤保险和生育保 险药品目录》及《医保药品分类与代码数据 库》中有适应症支付限定的药品进行监管。"
    },
    {
      "official_code": "GZ10000101009000",
      "tier1": "政策类",
      "tier2": "药品政策限定类",
      "tier1_id": "policy",
      "tier2_id": "drug_policy",
      "name": "药品限最大支付天数/开药量",
      "definition": "对政策中有限定最大支付天数/支付量的药品 进行监管。"
    },
    {
      "official_code": "GZ10000101010000",
      "tier1": "政策类",
      "tier2": "药品政策限定类",
      "tier1_id": "policy",
      "tier2_id": "drug_policy",
      "name": "药品限支付疗程",
      "definition": "对《国家基本医疗保险、工伤保险和生育保 险药品目录》及《医保药品分类与代码数据 库》中，有限定使用疗程的药品进行监管。"
    },
    {
      "official_code": "GZ10000101011000",
      "tier1": "政策类",
      "tier2": "药品政策限定类",
      "tier1_id": "policy",
      "tier2_id": "drug_policy",
      "name": "药品超限定病种目录范围使用对各级医保政策中有限定病种目录范围使用的药品进行监管。1规则编码一级分类二级分类规则名称定义",
      "definition": "政策类药品政策限定类 药品超限定病种目录范围 使用 对各级医保政策中有限定病种目录范围使用 的药品进行监管。 1 规则编码一级分类二级分类规则名称定义"
    },
    {
      "official_code": "GZ10000101012000",
      "tier1": "政策类",
      "tier2": "药品政策限定类",
      "tier1_id": "policy",
      "tier2_id": "drug_policy",
      "name": "药品限医疗机构级别",
      "definition": "对《国家基本医疗保险、工伤保险和生育保 险药品目录》及《医保药品分类与代码数据 库》中有限医疗机构级别使用的药品进行监 管。"
    },
    {
      "official_code": "GZ10000102001000",
      "tier1": "政策类",
      "tier2": "医疗服务项目政策限定类",
      "tier1_id": "policy",
      "tier2_id": "service_policy",
      "name": "医疗服务项目超限定单价收费",
      "definition": "对最新版医疗服务项目分类与代码中限定单 价的医疗服务项目进行监管。"
    },
    {
      "official_code": "GZ10000102002000",
      "tier1": "政策类",
      "tier2": "医疗服务项目政策限定类",
      "tier1_id": "policy",
      "tier2_id": "service_policy",
      "name": "手术项目未按规定折价收费",
      "definition": "对最新版医疗服务项目分类与代码中手术项 目的折价计费情况进行监管。"
    },
    {
      "official_code": "GZ10000102003000",
      "tier1": "政策类",
      "tier2": "医疗服务项目政策限定类",
      "tier1_id": "policy",
      "tier2_id": "service_policy",
      "name": "医疗服务项目限工伤保险",
      "definition": "对最新版医疗服务项目分类与代码对限工伤 保险的医疗服务项目进行监管。"
    },
    {
      "official_code": "GZ10000102004000",
      "tier1": "政策类",
      "tier2": "医疗服务项目政策限定类",
      "tier1_id": "policy",
      "tier2_id": "service_policy",
      "name": "医疗服务项目限生育保险",
      "definition": "对最新版医疗服务项目分类与代码对限生育 保险的医疗服务项目进行监管。"
    },
    {
      "official_code": "GZ10000102005000",
      "tier1": "政策类",
      "tier2": "医疗服务项目政策限定类",
      "tier1_id": "policy",
      "tier2_id": "service_policy",
      "name": "医疗服务项目限新生儿使用",
      "definition": "对最新版医疗服务项目分类与代码中限新生 儿使用的医疗服务项目进行监管。"
    },
    {
      "official_code": "GZ10000102006000",
      "tier1": "政策类",
      "tier2": "医疗服务项目政策限定类",
      "tier1_id": "policy",
      "tier2_id": "service_policy",
      "name": "医疗服务项目限儿童使用",
      "definition": "对最新版医疗服务项目分类与代码中限儿童 使用的医疗服务项目进行监管。"
    },
    {
      "official_code": "GZ10000102007000",
      "tier1": "政策类",
      "tier2": "医疗服务项目政策限定类",
      "tier1_id": "policy",
      "tier2_id": "service_policy",
      "name": "医疗服务项目限适应症",
      "definition": "对最新版医疗服务项目分类与代码中有适应 症支付限定的医疗服务项目进行监管。"
    },
    {
      "official_code": "GZ10000102008000",
      "tier1": "政策类",
      "tier2": "医疗服务项目政策限定类",
      "tier1_id": "policy",
      "tier2_id": "service_policy",
      "name": "医疗服务项目限科室使用",
      "definition": "对最新版医疗服务项目分类与代码中有限科 室使用的医疗服务项目进行监管。"
    },
    {
      "official_code": "GZ10000102009000",
      "tier1": "政策类",
      "tier2": "医疗服务项目政策限定类",
      "tier1_id": "policy",
      "tier2_id": "service_policy",
      "name": "医疗服务项目限就医方式",
      "definition": "对最新版医疗服务项目分类与代码中就医方 式支付限定的医疗服务项目进行监管。"
    },
    {
      "official_code": "GZ10000102010000",
      "tier1": "政策类",
      "tier2": "医疗服务项目政策限定类",
      "tier1_id": "policy",
      "tier2_id": "service_policy",
      "name": "医疗服务项目限支付疗程",
      "definition": "对最新版医疗服务项目分类与代码中限定支 付疗程的医疗服务项目进行监管。"
    },
    {
      "official_code": "GZ10000102011000",
      "tier1": "政策类",
      "tier2": "医疗服务项目政策限定类",
      "tier1_id": "policy",
      "tier2_id": "service_policy",
      "name": "医疗服务项目限医疗机构级别",
      "definition": "对最新版医疗服务项目分类与代码中有限医 疗机构级别使用的医疗服务项目进行监管。 2 规则编码一级分类二级分类规则名称定义"
    },
    {
      "official_code": "GZ10000102012000",
      "tier1": "政策类",
      "tier2": "医疗服务项目政策限定类",
      "tier1_id": "policy",
      "tier2_id": "service_policy",
      "name": "医疗服务项目重复收费",
      "definition": "对最新版医疗服务项目分类与代码中项目内 涵有包含与被包含关系或计价说明中明确规 定不得另行收费的医疗服务项目进行监管。"
    },
    {
      "official_code": "GZ10000102013000",
      "tier1": "政策类",
      "tier2": "医疗服务项目政策限定类",
      "tier1_id": "policy",
      "tier2_id": "service_policy",
      "name": "医疗服务项目分解收费",
      "definition": "对最新版医疗服务项目分类与代码中应合并 收费的医疗服务项目存在拆分为若干收费项 目的情形进行监管。"
    },
    {
      "official_code": "GZ10000102014000",
      "tier1": "政策类",
      "tier2": "医疗服务项目政策限定类",
      "tier1_id": "policy",
      "tier2_id": "service_policy",
      "name": "医疗服务项目限定频次",
      "definition": "对最新版医疗服务项目分类与代码中有使用 频次限定的医疗服务项目进行监管。"
    },
    {
      "official_code": "GZ10000102015000",
      "tier1": "政策类",
      "tier2": "医疗服务项目政策限定类",
      "tier1_id": "policy",
      "tier2_id": "service_policy",
      "name": "医疗服务项目超限定报销总额",
      "definition": "对最新版医疗服务项目分类与代码中有总额 支付限定的医疗服务项目进行监管。"
    },
    {
      "official_code": "GZ10000103001000",
      "tier1": "政策类",
      "tier2": "医用耗材政策限定类",
      "tier1_id": "policy",
      "tier2_id": "consumable_policy",
      "name": "耗材限新生儿使用",
      "definition": "对《医保医用耗材分类与代码数据库》中限 新生儿使用的医用耗材进行监管。"
    },
    {
      "official_code": "GZ10000103002000",
      "tier1": "政策类",
      "tier2": "医用耗材政策限定类",
      "tier1_id": "policy",
      "tier2_id": "consumable_policy",
      "name": "耗材限儿童使用",
      "definition": "对《医保医用耗材分类与代码数据库》中限 儿童使用的耗材进行监管。"
    },
    {
      "official_code": "GZ10000103003000",
      "tier1": "政策类",
      "tier2": "医用耗材政策限定类",
      "tier1_id": "policy",
      "tier2_id": "consumable_policy",
      "name": "耗材超限定报销总额",
      "definition": "对《医保医用耗材分类与代码数据库》中有 限定报销总额的耗材进行监管。"
    },
    {
      "official_code": "GZ10000201001000",
      "tier1": "管理类",
      "tier2": "信息数据监管类",
      "tier1_id": "management",
      "tier2_id": "data_supervision",
      "name": "医保结算清单信息异常对医保结算清单中数据指标填写的完整性、合理性和规范性进行审核。",
      "definition": "管理类信息数据监管类医保结算清单信息异常 对医保结算清单中数据指标填写的完整性、 合理性和规范性进行审核。"
    },
    {
      "official_code": "GZ10000201002000",
      "tier1": "管理类",
      "tier2": "信息数据监管类",
      "tier1_id": "management",
      "tier2_id": "data_supervision",
      "name": "结算明细信息异常对结算明细信息缺失、错误的情形进行监管。",
      "definition": "管理类信息数据监管类结算明细信息异常 对结算明细信息缺失、错误的情形进行监管 。"
    },
    {
      "official_code": "GZ10000201003000",
      "tier1": "管理类",
      "tier2": "信息数据监管类",
      "tier1_id": "management",
      "tier2_id": "data_supervision",
      "name": "疾病诊断编码异常对医保结算清单中填写的诊断编码在结算明细中无对应医疗服务项目（或药品、医用耗材）的情形进行监管。",
      "definition": "管理类信息数据监管类疾病诊断编码异常 对医保结算清单中填写的诊断编码在结算明 细中无对应医疗服务项目（或药品、医用耗 材）的情形进行监管。"
    },
    {
      "official_code": "GZ10000201004000",
      "tier1": "管理类",
      "tier2": "信息数据监管类",
      "tier1_id": "management",
      "tier2_id": "data_supervision",
      "name": "手术操作编码异常对医保结算清单中手术操作编码信息缺失、错编、主手术选择错误情形进行监管。",
      "definition": "管理类信息数据监管类手术操作编码异常 对医保结算清单中手术操作编码信息缺失、 错编、主手术选择错误情形进行监管。"
    },
    {
      "official_code": "GZ10000201005000",
      "tier1": "管理类",
      "tier2": "信息数据监管类",
      "tier1_id": "management",
      "tier2_id": "data_supervision",
      "name": "手术操作编码与性别不符对医保结算清单中手术操作编码与参保人性别不符的情形进行监管。3规则编码一级分类二级分类规则名称定义",
      "definition": "管理类信息数据监管类手术操作编码与性别不符 对医保结算清单中手术操作编码与参保人性 别不符的情形进行监管。 3 规则编码一级分类二级分类规则名称定义"
    },
    {
      "official_code": "GZ10000201006000",
      "tier1": "管理类",
      "tier2": "信息数据监管类",
      "tier1_id": "management",
      "tier2_id": "data_supervision",
      "name": "诊断编码与手术操作编码不符对医保结算清单中主要诊断编码和主要手术操作编码的相关性进行监管。",
      "definition": "管理类信息数据监管类 诊断编码与手术操作编码 不符 对医保结算清单中主要诊断编码和主要手术 操作编码的相关性进行监管。"
    },
    {
      "official_code": "GZ10000201007000",
      "tier1": "管理类",
      "tier2": "信息数据监管类",
      "tier1_id": "management",
      "tier2_id": "data_supervision",
      "name": "就诊数据非实时上传监管对就诊数据中费用明细开具时间进行监管。",
      "definition": "管理类信息数据监管类就诊数据非实时上传监管对就诊数据中费用明细开具时间进行监管。"
    },
    {
      "official_code": "GZ10000201008000",
      "tier1": "管理类",
      "tier2": "信息数据监管类",
      "tier1_id": "management",
      "tier2_id": "data_supervision",
      "name": "计费日期与住院时间不符对收费项计费日期不在住院时间范围内的情况进行监管。",
      "definition": "管理类信息数据监管类计费日期与住院时间不符 对收费项计费日期不在住院时间范围内的情 况进行监管。"
    },
    {
      "official_code": "GZ10000202001000",
      "tier1": "管理类",
      "tier2": "药品监管类",
      "tier1_id": "management",
      "tier2_id": "drug_supervision",
      "name": "-管理要求药品进销存异常",
      "definition": "对《国家基本医疗保险、工伤保险和生育保 险药品目录》及《医保药品分类与代码数据 库》中药品的进销存数据进行监管。"
    },
    {
      "official_code": "GZ10000202002000",
      "tier1": "管理类",
      "tier2": "药品监管类",
      "tier1_id": "management",
      "tier2_id": "drug_supervision",
      "name": "-管理要求围手术期抗菌药物预防性应用监管",
      "definition": "对《国家基本医疗保险、工伤保险和生育保 险药品目录》及《医保药品分类与代码数据 库》中抗菌药物的围手术期预防性应用情况 进行监管。"
    },
    {
      "official_code": "GZ10000202003000",
      "tier1": "管理类",
      "tier2": "药品监管类",
      "tier1_id": "management",
      "tier2_id": "drug_supervision",
      "name": "-管理要求抗菌药物分级使用管理",
      "definition": "对《国家基本医疗保险、工伤保险和生育保 险药品目录》及《医保药品分类与代码数据 库》中抗菌药物的分级使用情况进行监管。"
    },
    {
      "official_code": "GZ10000202004000",
      "tier1": "管理类",
      "tier2": "药品监管类",
      "tier1_id": "management",
      "tier2_id": "drug_supervision",
      "name": "-管理要求药品种类超标",
      "definition": "对《国家基本医疗保险、工伤保险和生育保 险药品目录》及《医保药品分类与代码数据 库》中的药品进行日常开药种类的监管。"
    },
    {
      "official_code": "GZ10000203001000",
      "tier1": "管理类",
      "tier2": "医用耗材监管类",
      "tier1_id": "management",
      "tier2_id": "consumable_supervision",
      "name": "-管理要求医用耗材进销存异常",
      "definition": "对《医保医用耗材分类与代码数据库》中耗 材的进销存数据进行监管。"
    },
    {
      "official_code": "GZ10000204001000",
      "tier1": "管理类",
      "tier2": "行为主体监管类",
      "tier1_id": "management",
      "tier2_id": "actor_supervision",
      "name": "分解住院",
      "definition": "对参保人在非特殊情况下，在同一家医疗机 构相邻的两次住院间隔异常情形进行监管。"
    },
    {
      "official_code": "GZ10000204002000",
      "tier1": "管理类",
      "tier2": "行为主体监管类",
      "tier1_id": "management",
      "tier2_id": "actor_supervision",
      "name": "频繁门诊对单位时间区内参保人门诊就医次数超出设定次数的情形进行监管。",
      "definition": "管理类行为主体监管类频繁门诊 对单位时间区内参保人门诊就医次数超出设 定次数的情形进行监管。"
    },
    {
      "official_code": "GZ10000204003000",
      "tier1": "管理类",
      "tier2": "行为主体监管类",
      "tier1_id": "management",
      "tier2_id": "actor_supervision",
      "name": "频繁购药",
      "definition": "对参保人单位时间内购药次数进行监管。"
    },
    {
      "official_code": "GZ10000204004000",
      "tier1": "管理类",
      "tier2": "行为主体监管类",
      "tier1_id": "management",
      "tier2_id": "actor_supervision",
      "name": "频繁住院",
      "definition": "对参保人单位时间内多次发生住院行为进行 监管。 4 规则编码一级分类二级分类规则名称定义"
    },
    {
      "official_code": "GZ10000204005000",
      "tier1": "管理类",
      "tier2": "行为主体监管类",
      "tier1_id": "management",
      "tier2_id": "actor_supervision",
      "name": "无指征住院（低标准入院）",
      "definition": "对参保人不满足住院标准而发生住院行为的 情形进行监管。"
    },
    {
      "official_code": "GZ10000204006000",
      "tier1": "管理类",
      "tier2": "行为主体监管类",
      "tier1_id": "management",
      "tier2_id": "actor_supervision",
      "name": "诊断与患者性别不符",
      "definition": "对参保人诊断与性别不符的情形进行监管。"
    },
    {
      "official_code": "GZ10000204007000",
      "tier1": "管理类",
      "tier2": "行为主体监管类",
      "tier1_id": "management",
      "tier2_id": "actor_supervision",
      "name": "诊断与患者年龄不符",
      "definition": "对参保人诊断与年龄不符情形进行监管。"
    },
    {
      "official_code": "ZB10000205001000",
      "tier1": "管理类",
      "tier2": "统计指标监测类",
      "tier1_id": "management",
      "tier2_id": "stats_monitoring",
      "name": "药费占比统计",
      "definition": "对《国家基本医疗保险、工伤保险和生育保 险药品目录》及《医保药品分类与代码数据 库》中的药品费用与总费用比值进行监管。"
    },
    {
      "official_code": "ZB10000205002000",
      "tier1": "管理类",
      "tier2": "统计指标监测类",
      "tier1_id": "management",
      "tier2_id": "stats_monitoring",
      "name": "检验检查占比统计",
      "definition": "对最新版医疗服务项目分类与代码中检验检 查费用与总费用比值进行监管。"
    },
    {
      "official_code": "ZB10000205003000",
      "tier1": "管理类",
      "tier2": "统计指标监测类",
      "tier1_id": "management",
      "tier2_id": "stats_monitoring",
      "name": "耗材占比统计",
      "definition": "对最新版医疗服务项目分类与代码中耗材费 用与总费用比值进行监管。"
    },
    {
      "official_code": "ZB10000205004000",
      "tier1": "管理类",
      "tier2": "统计指标监测类",
      "tier1_id": "management",
      "tier2_id": "stats_monitoring",
      "name": "治疗占比统计",
      "definition": "对最新版医疗服务项目分类与代码中治疗费 用与总费用比值进行监管。"
    },
    {
      "official_code": "ZB10000205005000",
      "tier1": "管理类",
      "tier2": "统计指标监测类",
      "tier1_id": "management",
      "tier2_id": "stats_monitoring",
      "name": "CT检查占比统计",
      "definition": "对最新版医疗服务项目分类与代码中CT检查 费用与总费用比值进行监管。"
    },
    {
      "official_code": "ZB10000205006000",
      "tier1": "管理类",
      "tier2": "统计指标监测类",
      "tier1_id": "management",
      "tier2_id": "stats_monitoring",
      "name": "核磁检查占比统计",
      "definition": "对最新版医疗服务项目分类与代码中核磁检 查费用与总费用比值进行监管。"
    },
    {
      "official_code": "ZB10000205007000",
      "tier1": "管理类",
      "tier2": "统计指标监测类",
      "tier1_id": "management",
      "tier2_id": "stats_monitoring",
      "name": "院内感染发生率统计对院内感染发生的情况进行监管。",
      "definition": "管理类统计指标监测类院内感染发生率统计对院内感染发生的情况进行监管。"
    },
    {
      "official_code": "ZB10000205008000",
      "tier1": "管理类",
      "tier2": "统计指标监测类",
      "tier1_id": "management",
      "tier2_id": "stats_monitoring",
      "name": "非计划再入院率统计对31天内非计划再入院发生的情况进行监管。",
      "definition": "管理类统计指标监测类非计划再入院率统计 对31天内非计划再入院发生的情况进行监管 。"
    },
    {
      "official_code": "GZ10000301001000",
      "tier1": "医疗类",
      "tier2": "药品合理使用类",
      "tier1_id": "medical",
      "tier2_id": "drug_rational",
      "name": "药品与医疗服务项目不符",
      "definition": "对《国家基本医疗保险、工伤保险和生育保 险药品目录》及《医保药品分类与代码数据 库》中需与特定医疗服务项目同时使用的药 品进行监管。 5 规则编码一级分类二级分类规则名称定义"
    },
    {
      "official_code": "GZ10000301002000",
      "tier1": "医疗类",
      "tier2": "药品合理使用类",
      "tier1_id": "medical",
      "tier2_id": "drug_rational",
      "name": "药品儿童专用对仅适用于儿童的药物进行监管。",
      "definition": "医疗类药品合理使用类药品儿童专用对仅适用于儿童的药物进行监管。"
    },
    {
      "official_code": "GZ10000301003000",
      "tier1": "医疗类",
      "tier2": "药品合理使用类",
      "tier1_id": "medical",
      "tier2_id": "drug_rational",
      "name": "药品儿童禁用对儿童禁忌使用的药物进行监管。",
      "definition": "医疗类药品合理使用类药品儿童禁用对儿童禁忌使用的药物进行监管。"
    },
    {
      "official_code": "GZ10000301004000",
      "tier1": "医疗类",
      "tier2": "药品合理使用类",
      "tier1_id": "medical",
      "tier2_id": "drug_rational",
      "name": "药品区分性别使用",
      "definition": "对《国家基本医疗保险、工伤保险和生育保 险药品目录》及《医保药品分类与代码数据 库》区分性别使用的药品进行监管。"
    },
    {
      "official_code": "GZ10000301005000",
      "tier1": "医疗类",
      "tier2": "药品合理使用类",
      "tier1_id": "medical",
      "tier2_id": "drug_rational",
      "name": "超说明书用量开药对超说明书给定剂量范围开药情形进行监管。",
      "definition": "医疗类药品合理使用类超说明书用量开药 对超说明书给定剂量范围开药情形进行监管 。"
    },
    {
      "official_code": "GZ10000301006000",
      "tier1": "医疗类",
      "tier2": "药品合理使用类",
      "tier1_id": "medical",
      "tier2_id": "drug_rational",
      "name": "重复开药",
      "definition": "对《国家基本医疗保险、工伤保险和生育保 险药品目录》及《医保药品分类与代码数据 库》中同时开具两种及以上药理作用相似的 药品进行监管。"
    },
    {
      "official_code": "GZ10000301007000",
      "tier1": "医疗类",
      "tier2": "药品合理使用类",
      "tier1_id": "medical",
      "tier2_id": "drug_rational",
      "name": "超说明书适应症用药",
      "definition": "对未按照说明书给定适应症范围开药情形进 行监管。"
    },
    {
      "official_code": "GZ10000301008000",
      "tier1": "医疗类",
      "tier2": "药品合理使用类",
      "tier1_id": "medical",
      "tier2_id": "drug_rational",
      "name": "药品禁忌症",
      "definition": "对《国家基本医疗保险、工伤保险和生育保 险药品目录》及《医保药品分类与代码数据 库》中有禁忌症的药品进行监管。"
    },
    {
      "official_code": "GZ10000301009000",
      "tier1": "医疗类",
      "tier2": "药品合理使用类",
      "tier1_id": "medical",
      "tier2_id": "drug_rational",
      "name": "老年人用药安全",
      "definition": "对《国家基本医疗保险、工伤保险和生育保 险药品目录》及《医保药品分类与代码数据 库》中有老年人使用禁忌的药品进行监管。"
    },
    {
      "official_code": "GZ10000301010000",
      "tier1": "医疗类",
      "tier2": "药品合理使用类",
      "tier1_id": "medical",
      "tier2_id": "drug_rational",
      "name": "妊娠期及哺乳期用药安全",
      "definition": "对《国家基本医疗保险、工伤保险和生育保 险药品目录》及《医保药品分类与代码数据 库》中有妊娠期或哺乳期人群禁忌的药品进 行监管。"
    },
    {
      "official_code": "GZ10000301011000",
      "tier1": "医疗类",
      "tier2": "药品合理使用类",
      "tier1_id": "medical",
      "tier2_id": "drug_rational",
      "name": "药品相互作用",
      "definition": "对《国家基本医疗保险、工伤保险和生育保 险药品目录》及《医保药品分类与代码数据 库》中有不良相互作用的药品进行监管。"
    },
    {
      "official_code": "GZ10000301012000",
      "tier1": "医疗类",
      "tier2": "药品合理使用类",
      "tier1_id": "medical",
      "tier2_id": "drug_rational",
      "name": "中药饮片配伍禁忌",
      "definition": "对《国家基本医疗保险、工伤保险和生育保 险药品目录》及《医保药品分类与代码数据 库》的中药饮片配伍进行监管。"
    },
    {
      "official_code": "GZ10000302001000",
      "tier1": "医疗类",
      "tier2": "医疗服务项目合理使用类",
      "tier1_id": "medical",
      "tier2_id": "service_rational",
      "name": "无指征检验检查",
      "definition": "对检验检查无相应适应症等情形进行监管。 6 规则编码一级分类二级分类规则名称定义"
    },
    {
      "official_code": "GZ10000302002000",
      "tier1": "医疗类",
      "tier2": "医疗服务项目合理使用类",
      "tier1_id": "medical",
      "tier2_id": "service_rational",
      "name": "无指征治疗",
      "definition": "对最新版医疗服务项目分类与代码中与疾病 无关或无治疗依据而反复多次使用的医疗服 务项目进行监管。"
    },
    {
      "official_code": "GZ10000302003000",
      "tier1": "医疗类",
      "tier2": "医疗服务项目合理使用类",
      "tier1_id": "medical",
      "tier2_id": "service_rational",
      "name": "医疗服务项目儿童专用",
      "definition": "对最新版医疗服务项目分类与代码中儿童专 用的医疗服务项目进行监管。"
    },
    {
      "official_code": "GZ10000302004000",
      "tier1": "医疗类",
      "tier2": "医疗服务项目合理使用类",
      "tier1_id": "medical",
      "tier2_id": "service_rational",
      "name": "医疗服务项目区分性别使用",
      "definition": "对最新版医疗服务项目分类与代码区分性别 使用的医疗服务项目进行监管。"
    },
    {
      "official_code": "GZ10000302005000",
      "tier1": "医疗类",
      "tier2": "医疗服务项目合理使用类",
      "tier1_id": "medical",
      "tier2_id": "service_rational",
      "name": "医疗服务项目禁忌症",
      "definition": "对最新版医疗服务项目分类与代码中有禁忌 症的医疗服务项目进行监管。"
    },
    {
      "official_code": "GZ10000302006000",
      "tier1": "医疗类",
      "tier2": "医疗服务项目合理使用类",
      "tier1_id": "medical",
      "tier2_id": "service_rational",
      "name": "医疗服务项目超适应症使用",
      "definition": "对未按照适应症范围使用医疗服务项目的情 形进行监管。"
    },
    {
      "official_code": "GZ10000303001000",
      "tier1": "医疗类",
      "tier2": "医用耗材合理使用类",
      "tier1_id": "medical",
      "tier2_id": "consumable_rational",
      "name": "医用耗材与医疗服务项目不符",
      "definition": "对《医保医用耗材分类与代码数据库》中需 与特定医疗服务项目同时使用的耗材进行监 管。"
    },
    {
      "official_code": "GZ10000303002000",
      "tier1": "医疗类",
      "tier2": "医用耗材合理使用类",
      "tier1_id": "medical",
      "tier2_id": "consumable_rational",
      "name": "医用耗材与科室不符",
      "definition": "对《医保医用耗材分类与代码数据库》中需 在特定科室使用的耗材进行监管。"
    },
    {
      "official_code": "GZ10000303003000",
      "tier1": "医疗类",
      "tier2": "医用耗材合理使用类",
      "tier1_id": "medical",
      "tier2_id": "consumable_rational",
      "name": "医用耗材数量超标",
      "definition": "对《医保医用耗材分类与代码数据库》中有 使用数量限定的耗材进行监管。"
    }
  ],
  "tier1": [
    {
      "id": "policy",
      "label": "政策类",
      "count": 30,
      "tier2": [
        {
          "id": "drug_policy",
          "label": "药品政策限定类",
          "count": 12,
          "rules": [
            {
              "official_code": "GZ10000101001000",
              "name": "药品限工伤保险",
              "definition": "对《国家基本医疗保险、工伤保险和生育保 险药品目录》及《医保药品分类与代码数据 库》对限工伤保险的药品进行监管。"
            },
            {
              "official_code": "GZ10000101002000",
              "name": "药品限生育保险",
              "definition": "对《国家基本医疗保险、工伤保险和生育保 险药品目录》及《医保药品分类与代码数据 库》对限生育保险的药品进行监管。"
            },
            {
              "official_code": "GZ10000101003000",
              "name": "中药饮片单复方均不予支付",
              "definition": "对《国家基本医疗保险、工伤保险和生育保 险药品目录》及《医保药品分类与代码数据 库》对不得纳入基金支付范围的中药饮片进 行监管。"
            },
            {
              "official_code": "GZ10000101004000",
              "name": "中药饮片单方使用不予支付",
              "definition": "对《国家基本医疗保险、工伤保险和生育保 险药品目录》及《医保药品分类与代码数据 库》对单独使用且全部由这些饮片组成的处 方也不予支付的中药饮片进行监管。"
            },
            {
              "official_code": "GZ10000101005000",
              "name": "药品限二线使用",
              "definition": "对《国家基本医疗保险、工伤保险和生育保 险药品目录》及《医保药品分类与代码数据 库》中限二线使用的药品进行监管。"
            },
            {
              "official_code": "GZ10000101006000",
              "name": "药品限新生儿使用",
              "definition": "对《国家基本医疗保险、工伤保险和生育保 险药品目录》及《医保药品分类与代码数据 库》中限新生儿使用的药品进行监管。"
            },
            {
              "official_code": "GZ10000101007000",
              "name": "药品限儿童使用",
              "definition": "对《国家基本医疗保险、工伤保险和生育保 险药品目录》及《医保药品分类与代码数据 库》中限儿童使用的药品进行监管。"
            },
            {
              "official_code": "GZ10000101008000",
              "name": "药品限适应症",
              "definition": "对《国家基本医疗保险、工伤保险和生育保 险药品目录》及《医保药品分类与代码数据 库》中有适应症支付限定的药品进行监管。"
            },
            {
              "official_code": "GZ10000101009000",
              "name": "药品限最大支付天数/开药量",
              "definition": "对政策中有限定最大支付天数/支付量的药品 进行监管。"
            },
            {
              "official_code": "GZ10000101010000",
              "name": "药品限支付疗程",
              "definition": "对《国家基本医疗保险、工伤保险和生育保 险药品目录》及《医保药品分类与代码数据 库》中，有限定使用疗程的药品进行监管。"
            },
            {
              "official_code": "GZ10000101011000",
              "name": "药品超限定病种目录范围使用对各级医保政策中有限定病种目录范围使用的药品进行监管。1规则编码一级分类二级分类规则名称定义",
              "definition": "政策类药品政策限定类 药品超限定病种目录范围 使用 对各级医保政策中有限定病种目录范围使用 的药品进行监管。 1 规则编码一级分类二级分类规则名称定义"
            },
            {
              "official_code": "GZ10000101012000",
              "name": "药品限医疗机构级别",
              "definition": "对《国家基本医疗保险、工伤保险和生育保 险药品目录》及《医保药品分类与代码数据 库》中有限医疗机构级别使用的药品进行监 管。"
            }
          ]
        },
        {
          "id": "service_policy",
          "label": "医疗服务项目政策限定类",
          "count": 15,
          "rules": [
            {
              "official_code": "GZ10000102001000",
              "name": "医疗服务项目超限定单价收费",
              "definition": "对最新版医疗服务项目分类与代码中限定单 价的医疗服务项目进行监管。"
            },
            {
              "official_code": "GZ10000102002000",
              "name": "手术项目未按规定折价收费",
              "definition": "对最新版医疗服务项目分类与代码中手术项 目的折价计费情况进行监管。"
            },
            {
              "official_code": "GZ10000102003000",
              "name": "医疗服务项目限工伤保险",
              "definition": "对最新版医疗服务项目分类与代码对限工伤 保险的医疗服务项目进行监管。"
            },
            {
              "official_code": "GZ10000102004000",
              "name": "医疗服务项目限生育保险",
              "definition": "对最新版医疗服务项目分类与代码对限生育 保险的医疗服务项目进行监管。"
            },
            {
              "official_code": "GZ10000102005000",
              "name": "医疗服务项目限新生儿使用",
              "definition": "对最新版医疗服务项目分类与代码中限新生 儿使用的医疗服务项目进行监管。"
            },
            {
              "official_code": "GZ10000102006000",
              "name": "医疗服务项目限儿童使用",
              "definition": "对最新版医疗服务项目分类与代码中限儿童 使用的医疗服务项目进行监管。"
            },
            {
              "official_code": "GZ10000102007000",
              "name": "医疗服务项目限适应症",
              "definition": "对最新版医疗服务项目分类与代码中有适应 症支付限定的医疗服务项目进行监管。"
            },
            {
              "official_code": "GZ10000102008000",
              "name": "医疗服务项目限科室使用",
              "definition": "对最新版医疗服务项目分类与代码中有限科 室使用的医疗服务项目进行监管。"
            },
            {
              "official_code": "GZ10000102009000",
              "name": "医疗服务项目限就医方式",
              "definition": "对最新版医疗服务项目分类与代码中就医方 式支付限定的医疗服务项目进行监管。"
            },
            {
              "official_code": "GZ10000102010000",
              "name": "医疗服务项目限支付疗程",
              "definition": "对最新版医疗服务项目分类与代码中限定支 付疗程的医疗服务项目进行监管。"
            },
            {
              "official_code": "GZ10000102011000",
              "name": "医疗服务项目限医疗机构级别",
              "definition": "对最新版医疗服务项目分类与代码中有限医 疗机构级别使用的医疗服务项目进行监管。 2 规则编码一级分类二级分类规则名称定义"
            },
            {
              "official_code": "GZ10000102012000",
              "name": "医疗服务项目重复收费",
              "definition": "对最新版医疗服务项目分类与代码中项目内 涵有包含与被包含关系或计价说明中明确规 定不得另行收费的医疗服务项目进行监管。"
            },
            {
              "official_code": "GZ10000102013000",
              "name": "医疗服务项目分解收费",
              "definition": "对最新版医疗服务项目分类与代码中应合并 收费的医疗服务项目存在拆分为若干收费项 目的情形进行监管。"
            },
            {
              "official_code": "GZ10000102014000",
              "name": "医疗服务项目限定频次",
              "definition": "对最新版医疗服务项目分类与代码中有使用 频次限定的医疗服务项目进行监管。"
            },
            {
              "official_code": "GZ10000102015000",
              "name": "医疗服务项目超限定报销总额",
              "definition": "对最新版医疗服务项目分类与代码中有总额 支付限定的医疗服务项目进行监管。"
            }
          ]
        },
        {
          "id": "consumable_policy",
          "label": "医用耗材政策限定类",
          "count": 3,
          "rules": [
            {
              "official_code": "GZ10000103001000",
              "name": "耗材限新生儿使用",
              "definition": "对《医保医用耗材分类与代码数据库》中限 新生儿使用的医用耗材进行监管。"
            },
            {
              "official_code": "GZ10000103002000",
              "name": "耗材限儿童使用",
              "definition": "对《医保医用耗材分类与代码数据库》中限 儿童使用的耗材进行监管。"
            },
            {
              "official_code": "GZ10000103003000",
              "name": "耗材超限定报销总额",
              "definition": "对《医保医用耗材分类与代码数据库》中有 限定报销总额的耗材进行监管。"
            }
          ]
        }
      ]
    },
    {
      "id": "management",
      "label": "管理类",
      "count": 28,
      "tier2": [
        {
          "id": "data_supervision",
          "label": "信息数据监管类",
          "count": 8,
          "rules": [
            {
              "official_code": "GZ10000201001000",
              "name": "医保结算清单信息异常对医保结算清单中数据指标填写的完整性、合理性和规范性进行审核。",
              "definition": "管理类信息数据监管类医保结算清单信息异常 对医保结算清单中数据指标填写的完整性、 合理性和规范性进行审核。"
            },
            {
              "official_code": "GZ10000201002000",
              "name": "结算明细信息异常对结算明细信息缺失、错误的情形进行监管。",
              "definition": "管理类信息数据监管类结算明细信息异常 对结算明细信息缺失、错误的情形进行监管 。"
            },
            {
              "official_code": "GZ10000201003000",
              "name": "疾病诊断编码异常对医保结算清单中填写的诊断编码在结算明细中无对应医疗服务项目（或药品、医用耗材）的情形进行监管。",
              "definition": "管理类信息数据监管类疾病诊断编码异常 对医保结算清单中填写的诊断编码在结算明 细中无对应医疗服务项目（或药品、医用耗 材）的情形进行监管。"
            },
            {
              "official_code": "GZ10000201004000",
              "name": "手术操作编码异常对医保结算清单中手术操作编码信息缺失、错编、主手术选择错误情形进行监管。",
              "definition": "管理类信息数据监管类手术操作编码异常 对医保结算清单中手术操作编码信息缺失、 错编、主手术选择错误情形进行监管。"
            },
            {
              "official_code": "GZ10000201005000",
              "name": "手术操作编码与性别不符对医保结算清单中手术操作编码与参保人性别不符的情形进行监管。3规则编码一级分类二级分类规则名称定义",
              "definition": "管理类信息数据监管类手术操作编码与性别不符 对医保结算清单中手术操作编码与参保人性 别不符的情形进行监管。 3 规则编码一级分类二级分类规则名称定义"
            },
            {
              "official_code": "GZ10000201006000",
              "name": "诊断编码与手术操作编码不符对医保结算清单中主要诊断编码和主要手术操作编码的相关性进行监管。",
              "definition": "管理类信息数据监管类 诊断编码与手术操作编码 不符 对医保结算清单中主要诊断编码和主要手术 操作编码的相关性进行监管。"
            },
            {
              "official_code": "GZ10000201007000",
              "name": "就诊数据非实时上传监管对就诊数据中费用明细开具时间进行监管。",
              "definition": "管理类信息数据监管类就诊数据非实时上传监管对就诊数据中费用明细开具时间进行监管。"
            },
            {
              "official_code": "GZ10000201008000",
              "name": "计费日期与住院时间不符对收费项计费日期不在住院时间范围内的情况进行监管。",
              "definition": "管理类信息数据监管类计费日期与住院时间不符 对收费项计费日期不在住院时间范围内的情 况进行监管。"
            }
          ]
        },
        {
          "id": "drug_supervision",
          "label": "药品监管类",
          "count": 4,
          "rules": [
            {
              "official_code": "GZ10000202001000",
              "name": "-管理要求药品进销存异常",
              "definition": "对《国家基本医疗保险、工伤保险和生育保 险药品目录》及《医保药品分类与代码数据 库》中药品的进销存数据进行监管。"
            },
            {
              "official_code": "GZ10000202002000",
              "name": "-管理要求围手术期抗菌药物预防性应用监管",
              "definition": "对《国家基本医疗保险、工伤保险和生育保 险药品目录》及《医保药品分类与代码数据 库》中抗菌药物的围手术期预防性应用情况 进行监管。"
            },
            {
              "official_code": "GZ10000202003000",
              "name": "-管理要求抗菌药物分级使用管理",
              "definition": "对《国家基本医疗保险、工伤保险和生育保 险药品目录》及《医保药品分类与代码数据 库》中抗菌药物的分级使用情况进行监管。"
            },
            {
              "official_code": "GZ10000202004000",
              "name": "-管理要求药品种类超标",
              "definition": "对《国家基本医疗保险、工伤保险和生育保 险药品目录》及《医保药品分类与代码数据 库》中的药品进行日常开药种类的监管。"
            }
          ]
        },
        {
          "id": "consumable_supervision",
          "label": "医用耗材监管类",
          "count": 1,
          "rules": [
            {
              "official_code": "GZ10000203001000",
              "name": "-管理要求医用耗材进销存异常",
              "definition": "对《医保医用耗材分类与代码数据库》中耗 材的进销存数据进行监管。"
            }
          ]
        },
        {
          "id": "actor_supervision",
          "label": "行为主体监管类",
          "count": 7,
          "rules": [
            {
              "official_code": "GZ10000204001000",
              "name": "分解住院",
              "definition": "对参保人在非特殊情况下，在同一家医疗机 构相邻的两次住院间隔异常情形进行监管。"
            },
            {
              "official_code": "GZ10000204002000",
              "name": "频繁门诊对单位时间区内参保人门诊就医次数超出设定次数的情形进行监管。",
              "definition": "管理类行为主体监管类频繁门诊 对单位时间区内参保人门诊就医次数超出设 定次数的情形进行监管。"
            },
            {
              "official_code": "GZ10000204003000",
              "name": "频繁购药",
              "definition": "对参保人单位时间内购药次数进行监管。"
            },
            {
              "official_code": "GZ10000204004000",
              "name": "频繁住院",
              "definition": "对参保人单位时间内多次发生住院行为进行 监管。 4 规则编码一级分类二级分类规则名称定义"
            },
            {
              "official_code": "GZ10000204005000",
              "name": "无指征住院（低标准入院）",
              "definition": "对参保人不满足住院标准而发生住院行为的 情形进行监管。"
            },
            {
              "official_code": "GZ10000204006000",
              "name": "诊断与患者性别不符",
              "definition": "对参保人诊断与性别不符的情形进行监管。"
            },
            {
              "official_code": "GZ10000204007000",
              "name": "诊断与患者年龄不符",
              "definition": "对参保人诊断与年龄不符情形进行监管。"
            }
          ]
        },
        {
          "id": "stats_monitoring",
          "label": "统计指标监测类",
          "count": 8,
          "rules": [
            {
              "official_code": "ZB10000205001000",
              "name": "药费占比统计",
              "definition": "对《国家基本医疗保险、工伤保险和生育保 险药品目录》及《医保药品分类与代码数据 库》中的药品费用与总费用比值进行监管。"
            },
            {
              "official_code": "ZB10000205002000",
              "name": "检验检查占比统计",
              "definition": "对最新版医疗服务项目分类与代码中检验检 查费用与总费用比值进行监管。"
            },
            {
              "official_code": "ZB10000205003000",
              "name": "耗材占比统计",
              "definition": "对最新版医疗服务项目分类与代码中耗材费 用与总费用比值进行监管。"
            },
            {
              "official_code": "ZB10000205004000",
              "name": "治疗占比统计",
              "definition": "对最新版医疗服务项目分类与代码中治疗费 用与总费用比值进行监管。"
            },
            {
              "official_code": "ZB10000205005000",
              "name": "CT检查占比统计",
              "definition": "对最新版医疗服务项目分类与代码中CT检查 费用与总费用比值进行监管。"
            },
            {
              "official_code": "ZB10000205006000",
              "name": "核磁检查占比统计",
              "definition": "对最新版医疗服务项目分类与代码中核磁检 查费用与总费用比值进行监管。"
            },
            {
              "official_code": "ZB10000205007000",
              "name": "院内感染发生率统计对院内感染发生的情况进行监管。",
              "definition": "管理类统计指标监测类院内感染发生率统计对院内感染发生的情况进行监管。"
            },
            {
              "official_code": "ZB10000205008000",
              "name": "非计划再入院率统计对31天内非计划再入院发生的情况进行监管。",
              "definition": "管理类统计指标监测类非计划再入院率统计 对31天内非计划再入院发生的情况进行监管 。"
            }
          ]
        }
      ]
    },
    {
      "id": "medical",
      "label": "医疗类",
      "count": 21,
      "tier2": [
        {
          "id": "drug_rational",
          "label": "药品合理使用类",
          "count": 12,
          "rules": [
            {
              "official_code": "GZ10000301001000",
              "name": "药品与医疗服务项目不符",
              "definition": "对《国家基本医疗保险、工伤保险和生育保 险药品目录》及《医保药品分类与代码数据 库》中需与特定医疗服务项目同时使用的药 品进行监管。 5 规则编码一级分类二级分类规则名称定义"
            },
            {
              "official_code": "GZ10000301002000",
              "name": "药品儿童专用对仅适用于儿童的药物进行监管。",
              "definition": "医疗类药品合理使用类药品儿童专用对仅适用于儿童的药物进行监管。"
            },
            {
              "official_code": "GZ10000301003000",
              "name": "药品儿童禁用对儿童禁忌使用的药物进行监管。",
              "definition": "医疗类药品合理使用类药品儿童禁用对儿童禁忌使用的药物进行监管。"
            },
            {
              "official_code": "GZ10000301004000",
              "name": "药品区分性别使用",
              "definition": "对《国家基本医疗保险、工伤保险和生育保 险药品目录》及《医保药品分类与代码数据 库》区分性别使用的药品进行监管。"
            },
            {
              "official_code": "GZ10000301005000",
              "name": "超说明书用量开药对超说明书给定剂量范围开药情形进行监管。",
              "definition": "医疗类药品合理使用类超说明书用量开药 对超说明书给定剂量范围开药情形进行监管 。"
            },
            {
              "official_code": "GZ10000301006000",
              "name": "重复开药",
              "definition": "对《国家基本医疗保险、工伤保险和生育保 险药品目录》及《医保药品分类与代码数据 库》中同时开具两种及以上药理作用相似的 药品进行监管。"
            },
            {
              "official_code": "GZ10000301007000",
              "name": "超说明书适应症用药",
              "definition": "对未按照说明书给定适应症范围开药情形进 行监管。"
            },
            {
              "official_code": "GZ10000301008000",
              "name": "药品禁忌症",
              "definition": "对《国家基本医疗保险、工伤保险和生育保 险药品目录》及《医保药品分类与代码数据 库》中有禁忌症的药品进行监管。"
            },
            {
              "official_code": "GZ10000301009000",
              "name": "老年人用药安全",
              "definition": "对《国家基本医疗保险、工伤保险和生育保 险药品目录》及《医保药品分类与代码数据 库》中有老年人使用禁忌的药品进行监管。"
            },
            {
              "official_code": "GZ10000301010000",
              "name": "妊娠期及哺乳期用药安全",
              "definition": "对《国家基本医疗保险、工伤保险和生育保 险药品目录》及《医保药品分类与代码数据 库》中有妊娠期或哺乳期人群禁忌的药品进 行监管。"
            },
            {
              "official_code": "GZ10000301011000",
              "name": "药品相互作用",
              "definition": "对《国家基本医疗保险、工伤保险和生育保 险药品目录》及《医保药品分类与代码数据 库》中有不良相互作用的药品进行监管。"
            },
            {
              "official_code": "GZ10000301012000",
              "name": "中药饮片配伍禁忌",
              "definition": "对《国家基本医疗保险、工伤保险和生育保 险药品目录》及《医保药品分类与代码数据 库》的中药饮片配伍进行监管。"
            }
          ]
        },
        {
          "id": "service_rational",
          "label": "医疗服务项目合理使用类",
          "count": 6,
          "rules": [
            {
              "official_code": "GZ10000302001000",
              "name": "无指征检验检查",
              "definition": "对检验检查无相应适应症等情形进行监管。 6 规则编码一级分类二级分类规则名称定义"
            },
            {
              "official_code": "GZ10000302002000",
              "name": "无指征治疗",
              "definition": "对最新版医疗服务项目分类与代码中与疾病 无关或无治疗依据而反复多次使用的医疗服 务项目进行监管。"
            },
            {
              "official_code": "GZ10000302003000",
              "name": "医疗服务项目儿童专用",
              "definition": "对最新版医疗服务项目分类与代码中儿童专 用的医疗服务项目进行监管。"
            },
            {
              "official_code": "GZ10000302004000",
              "name": "医疗服务项目区分性别使用",
              "definition": "对最新版医疗服务项目分类与代码区分性别 使用的医疗服务项目进行监管。"
            },
            {
              "official_code": "GZ10000302005000",
              "name": "医疗服务项目禁忌症",
              "definition": "对最新版医疗服务项目分类与代码中有禁忌 症的医疗服务项目进行监管。"
            },
            {
              "official_code": "GZ10000302006000",
              "name": "医疗服务项目超适应症使用",
              "definition": "对未按照适应症范围使用医疗服务项目的情 形进行监管。"
            }
          ]
        },
        {
          "id": "consumable_rational",
          "label": "医用耗材合理使用类",
          "count": 3,
          "rules": [
            {
              "official_code": "GZ10000303001000",
              "name": "医用耗材与医疗服务项目不符",
              "definition": "对《医保医用耗材分类与代码数据库》中需 与特定医疗服务项目同时使用的耗材进行监 管。"
            },
            {
              "official_code": "GZ10000303002000",
              "name": "医用耗材与科室不符",
              "definition": "对《医保医用耗材分类与代码数据库》中需 在特定科室使用的耗材进行监管。"
            },
            {
              "official_code": "GZ10000303003000",
              "name": "医用耗材数量超标",
              "definition": "对《医保医用耗材分类与代码数据库》中有 使用数量限定的耗材进行监管。"
            }
          ]
        }
      ]
    }
  ]
}